<?xml version="1.0" encoding="UTF-8" standalone="no"?>
<window xmlns="http://schemas.haulmont.com/cuba/screen/window.xsd"
        caption="msg://editorCaption"
        focusComponent="fieldGroup"
        messagesPack="com.haulmont.sample.petclinic.web.visit.visit">
    <data>
        <instance id="visitDc"
                  class="com.haulmont.sample.petclinic.entity.visit.Visit"
                  view="visit-with-pet">
            <loader/>
        </instance>

        <collection id="petsDc" class="com.haulmont.sample.petclinic.entity.pet.Pet" view="_base">
            <loader>
                <query>
                    select e from petclinic_Pet e
                </query>
            </loader>
        </collection>
    </data>

    <dialogMode height="600"
                width="800"/>

    <layout expand="editActions" spacing="true">
        <form id="fieldGroup" dataContainer="visitDc">
            <column width="250px">
                <dateField property="visitStart"/>
                <dateField property="visitEnd"/>
                <textArea rows="5" property="description"/>
                <lookupPickerField property="pet" optionsContainer="petsDc"/>
            </column>
        </form>

        <hbox id="editActions" spacing="true">
            <button action="windowCommitAndClose"/>
            <button action="windowClose"/>
        </hbox>
    </layout>
</window>